download_stats/__init__.py
download_stats/main.py
download_stats/pepy.py
download_stats/pypistats.py
download_stats-2.0.1.dist-info/LICENSE
download_stats-2.0.1.dist-info/METADATA
download_stats-2.0.1.dist-info/WHEEL
download_stats-2.0.1.dist-info/entry_points.txt
download_stats-2.0.1.dist-info/top_level.txt
download_stats-2.0.1.dist-info/RECORD
