Metadata-Version: 2.1
Name: download_stats
Version: 2.0.1
Summary: Download stats for Python packages
Author-email: arj.python@gmail.com
Project-URL: Bug Reports, https://github.com/Abdur-RahmaanJ/download-stats/issues
Project-URL: Source, https://github.com/Abdur-RahmaanJ/download-stats/
Classifier: Development Status :: 4 - Beta
Classifier: Intended Audience :: Developers
Classifier: License :: OSI Approved :: MIT License
Classifier: Programming Language :: Python :: 3.7
Classifier: Programming Language :: Python :: 3.8
Classifier: Programming Language :: Python :: 3.9
Classifier: Programming Language :: Python :: 3.10
Classifier: Programming Language :: Python :: 3.11
Classifier: Programming Language :: Python :: 3.12
Classifier: Programming Language :: Python :: 3.13
Requires-Python: >=3.7
License-File: LICENSE
Requires-Dist: rich
Requires-Dist: requests
